Metadata-Version: 1.1
Name: pymybotvpnssh
Version: 3.1.0
Summary: A Python module for installing and configuring PyMyBot VPN
Home-page: https://github.com/Azigaming404
Author: Aji Permana
Author-email: admin@cybervpn.site
License: UNKNOWN
Platform: UNKNOWN
Classifier: Programming Language :: Python :: 3
Classifier: License :: OSI Approved :: MIT License
Classifier: Operating System :: OS Independent
